[[0, 0, 0], {"batch_size": 64, "kernel_size_1": 7, "lr": 0.08288640378009195, "num_filters_1": 98, "num_layers": 1, "optimizer": "Adam", "steps_to_train": 97, "weight_decay": 0.07379892982991222}, {"model_based_pick": false}]
[[0, 0, 1], {"batch_size": 128, "kernel_size_1": 7, "lr": 0.004056316372458691, "num_filters_1": 60, "num_layers": 3, "optimizer": "SGD", "steps_to_train": 47, "weight_decay": 0.1578230512527735, "kernel_size_2": 3, "kernel_size_3": 5, "num_filters_2": 38, "num_filters_3": 76}, {"model_based_pick": false}]
[[0, 0, 2], {"batch_size": 16, "kernel_size_1": 3, "lr": 0.056252929424425, "num_filters_1": 28, "num_layers": 4, "optimizer": "Adam", "steps_to_train": 10, "weight_decay": 0.021524038849677553, "kernel_size_2": 7, "kernel_size_3": 7, "kernel_size_4": 7, "num_filters_2": 68, "num_filters_3": 77, "num_filters_4": 60}, {"model_based_pick": false}]
[[0, 0, 3], {"batch_size": 128, "kernel_size_1": 3, "lr": 0.00393361418996215, "num_filters_1": 82, "num_layers": 5, "optimizer": "SGD", "steps_to_train": 32, "weight_decay": 0.0225597731974134, "kernel_size_2": 3, "kernel_size_3": 3, "kernel_size_4": 5, "kernel_size_5": 5, "num_filters_2": 105, "num_filters_3": 64, "num_filters_4": 88, "num_filters_5": 105}, {"model_based_pick": false}]
[[0, 0, 4], {"batch_size": 32, "kernel_size_1": 7, "lr": 0.018561545798366195, "num_filters_1": 20, "num_layers": 1, "optimizer": "SGD", "steps_to_train": 70, "weight_decay": 0.03735190106507672}, {"model_based_pick": false}]
[[0, 0, 5], {"batch_size": 16, "kernel_size_1": 7, "lr": 0.05378461901160956, "num_filters_1": 18, "num_layers": 4, "optimizer": "SGD", "steps_to_train": 97, "weight_decay": 0.014346791263730709, "kernel_size_2": 7, "kernel_size_3": 5, "kernel_size_4": 3, "num_filters_2": 17, "num_filters_3": 88, "num_filters_4": 24}, {"model_based_pick": false}]
[[0, 0, 6], {"batch_size": 16, "kernel_size_1": 5, "lr": 0.011528196356277215, "num_filters_1": 128, "num_layers": 4, "optimizer": "Adam", "steps_to_train": 44, "weight_decay": 0.13587935819938463, "kernel_size_2": 5, "kernel_size_3": 5, "kernel_size_4": 7, "num_filters_2": 87, "num_filters_3": 43, "num_filters_4": 22}, {"model_based_pick": false}]
[[0, 0, 7], {"batch_size": 16, "kernel_size_1": 5, "lr": 0.09205063534334343, "num_filters_1": 30, "num_layers": 4, "optimizer": "SGD", "steps_to_train": 86, "weight_decay": 0.024702011609731223, "kernel_size_2": 3, "kernel_size_3": 5, "kernel_size_4": 5, "num_filters_2": 20, "num_filters_3": 54, "num_filters_4": 19}, {"model_based_pick": false}]
[[0, 0, 8], {"batch_size": 16, "kernel_size_1": 7, "lr": 0.04450662088643104, "num_filters_1": 58, "num_layers": 1, "optimizer": "Adam", "steps_to_train": 38, "weight_decay": 0.03862349473381445}, {"model_based_pick": false}]
[[0, 0, 9], {"batch_size": 16, "kernel_size_1": 7, "lr": 0.008924747690826657, "num_filters_1": 21, "num_layers": 3, "optimizer": "SGD", "steps_to_train": 29, "weight_decay": 0.0729103334411877, "kernel_size_2": 3, "kernel_size_3": 5, "num_filters_2": 58, "num_filters_3": 113}, {"model_based_pick": false}]
[[0, 0, 10], {"batch_size": 32, "kernel_size_1": 5, "lr": 0.06165768239106525, "num_filters_1": 19, "num_layers": 4, "optimizer": "SGD", "steps_to_train": 51, "weight_decay": 0.012728253667985278, "kernel_size_2": 7, "kernel_size_3": 3, "kernel_size_4": 5, "num_filters_2": 17, "num_filters_3": 82, "num_filters_4": 104}, {"model_based_pick": false}]
[[0, 0, 11], {"batch_size": 128, "kernel_size_1": 5, "lr": 0.021067943835941978, "num_filters_1": 48, "num_layers": 1, "optimizer": "Adam", "steps_to_train": 52, "weight_decay": 0.030427985323910216}, {"model_based_pick": false}]
[[0, 0, 12], {"batch_size": 128, "kernel_size_1": 7, "lr": 0.0026302390387887334, "num_filters_1": 35, "num_layers": 5, "optimizer": "SGD", "steps_to_train": 89, "weight_decay": 0.042394650999464094, "kernel_size_2": 5, "kernel_size_3": 3, "kernel_size_4": 7, "kernel_size_5": 7, "num_filters_2": 64, "num_filters_3": 82, "num_filters_4": 24, "num_filters_5": 41}, {"model_based_pick": false}]
[[0, 0, 13], {"batch_size": 32, "kernel_size_1": 5, "lr": 0.0137312718183391, "num_filters_1": 117, "num_layers": 1, "optimizer": "SGD", "steps_to_train": 44, "weight_decay": 0.10657228784685138}, {"model_based_pick": false}]
[[0, 0, 14], {"batch_size": 64, "kernel_size_1": 5, "lr": 0.01896126902137336, "num_filters_1": 20, "num_layers": 5, "optimizer": "Adam", "steps_to_train": 39, "weight_decay": 0.08826177946302233, "kernel_size_2": 3, "kernel_size_3": 5, "kernel_size_4": 7, "kernel_size_5": 7, "num_filters_2": 108, "num_filters_3": 24, "num_filters_4": 21, "num_filters_5": 18}, {"model_based_pick": false}]
[[0, 0, 15], {"batch_size": 128, "kernel_size_1": 7, "lr": 0.015212297367138024, "num_filters_1": 30, "num_layers": 3, "optimizer": "SGD", "steps_to_train": 35, "weight_decay": 0.042376383150850995, "kernel_size_2": 3, "kernel_size_3": 5, "num_filters_2": 56, "num_filters_3": 51}, {"model_based_pick": false}]
[[0, 0, 16], {"batch_size": 64, "kernel_size_1": 7, "lr": 0.002244649579724208, "num_filters_1": 93, "num_layers": 2, "optimizer": "SGD", "steps_to_train": 50, "weight_decay": 0.16348916505198122, "kernel_size_2": 5, "num_filters_2": 21}, {"model_based_pick": false}]
[[0, 0, 17], {"batch_size": 16, "kernel_size_1": 5, "lr": 0.01311423944633553, "num_filters_1": 112, "num_layers": 2, "optimizer": "SGD", "steps_to_train": 39, "weight_decay": 0.08602828724901895, "kernel_size_2": 3, "num_filters_2": 70}, {"model_based_pick": false}]
[[0, 0, 18], {"batch_size": 32, "kernel_size_1": 3, "lr": 0.05547994954110869, "num_filters_1": 24, "num_layers": 4, "optimizer": "Adam", "steps_to_train": 77, "weight_decay": 0.031771715548891306, "kernel_size_2": 3, "kernel_size_3": 7, "kernel_size_4": 5, "num_filters_2": 36, "num_filters_3": 18, "num_filters_4": 23}, {"model_based_pick": false}]
[[0, 0, 19], {"batch_size": 64, "kernel_size_1": 7, "lr": 0.03612557256831663, "num_filters_1": 24, "num_layers": 2, "optimizer": "Adam", "steps_to_train": 68, "weight_decay": 0.05682584408202698, "kernel_size_2": 3, "num_filters_2": 114}, {"model_based_pick": false}]
[[0, 0, 20], {"batch_size": 16, "kernel_size_1": 5, "lr": 0.001940889864559935, "num_filters_1": 104, "num_layers": 2, "optimizer": "Adam", "steps_to_train": 80, "weight_decay": 0.022800299123046673, "kernel_size_2": 3, "num_filters_2": 29}, {"model_based_pick": false}]
[[0, 0, 21], {"batch_size": 32, "kernel_size_1": 5, "lr": 0.08310235717864542, "num_filters_1": 119, "num_layers": 4, "optimizer": "Adam", "steps_to_train": 87, "weight_decay": 0.021470593037884917, "kernel_size_2": 5, "kernel_size_3": 3, "kernel_size_4": 3, "num_filters_2": 78, "num_filters_3": 75, "num_filters_4": 23}, {"model_based_pick": false}]
[[0, 0, 22], {"batch_size": 128, "kernel_size_1": 3, "lr": 0.019905388989878852, "num_filters_1": 118, "num_layers": 4, "optimizer": "Adam", "steps_to_train": 91, "weight_decay": 0.01660989848953278, "kernel_size_2": 7, "kernel_size_3": 5, "kernel_size_4": 7, "num_filters_2": 16, "num_filters_3": 75, "num_filters_4": 30}, {"model_based_pick": false}]
[[0, 0, 23], {"batch_size": 16, "kernel_size_1": 7, "lr": 0.012308697697296294, "num_filters_1": 19, "num_layers": 1, "optimizer": "SGD", "steps_to_train": 98, "weight_decay": 0.028028760200407253}, {"model_based_pick": false}]
[[0, 0, 24], {"batch_size": 32, "kernel_size_1": 5, "lr": 0.010804771351553387, "num_filters_1": 25, "num_layers": 4, "optimizer": "SGD", "steps_to_train": 67, "weight_decay": 0.056975389901788916, "kernel_size_2": 5, "kernel_size_3": 3, "kernel_size_4": 7, "num_filters_2": 32, "num_filters_3": 32, "num_filters_4": 118}, {"model_based_pick": false}]
[[0, 0, 25], {"batch_size": 64, "kernel_size_1": 3, "lr": 0.0496737303545789, "num_filters_1": 59, "num_layers": 4, "optimizer": "Adam", "steps_to_train": 31, "weight_decay": 0.035932103799630626, "kernel_size_2": 3, "kernel_size_3": 7, "kernel_size_4": 3, "num_filters_2": 40, "num_filters_3": 47, "num_filters_4": 75}, {"model_based_pick": false}]
[[0, 0, 26], {"batch_size": 64, "kernel_size_1": 7, "lr": 0.08005839588212778, "num_filters_1": 28, "num_layers": 2, "optimizer": "Adam", "steps_to_train": 86, "weight_decay": 0.02014627911513222, "kernel_size_2": 3, "num_filters_2": 58}, {"model_based_pick": false}]
[[1, 0, 0], {"batch_size": 64, "kernel_size_1": 7, "lr": 0.0016393015391821149, "num_filters_1": 58, "num_layers": 3, "optimizer": "SGD", "steps_to_train": 24, "weight_decay": 0.01892267751184015, "kernel_size_2": 3, "kernel_size_3": 7, "num_filters_2": 66, "num_filters_3": 87}, {"model_based_pick": false}]
[[1, 0, 1], {"batch_size": 128, "kernel_size_1": 7, "lr": 0.02739507987243467, "num_filters_1": 106, "num_layers": 3, "optimizer": "SGD", "steps_to_train": 83, "weight_decay": 0.07114749262783128, "kernel_size_2": 5, "kernel_size_3": 3, "num_filters_2": 17, "num_filters_3": 38}, {"model_based_pick": false}]
[[1, 0, 2], {"batch_size": 64, "kernel_size_1": 3, "lr": 0.005851998391578542, "num_filters_1": 28, "num_layers": 3, "optimizer": "Adam", "steps_to_train": 30, "weight_decay": 0.011407473152465859, "kernel_size_2": 5, "kernel_size_3": 3, "num_filters_2": 105, "num_filters_3": 16}, {"model_based_pick": false}]
[[1, 0, 3], {"batch_size": 32, "kernel_size_1": 7, "lr": 0.09169666141413194, "num_filters_1": 18, "num_layers": 5, "optimizer": "SGD", "steps_to_train": 43, "weight_decay": 0.06315828139207157, "kernel_size_2": 3, "kernel_size_3": 7, "kernel_size_4": 3, "kernel_size_5": 3, "num_filters_2": 24, "num_filters_3": 42, "num_filters_4": 24, "num_filters_5": 44}, {"model_based_pick": false}]
[[1, 0, 4], {"batch_size": 16, "kernel_size_1": 3, "lr": 0.025378849846220953, "num_filters_1": 36, "num_layers": 5, "optimizer": "SGD", "steps_to_train": 93, "weight_decay": 0.015376608359894763, "kernel_size_2": 5, "kernel_size_3": 5, "kernel_size_4": 5, "kernel_size_5": 7, "num_filters_2": 30, "num_filters_3": 54, "num_filters_4": 17, "num_filters_5": 42}, {"model_based_pick": false}]
[[1, 0, 5], {"batch_size": 128, "kernel_size_1": 7, "lr": 0.020028032583103796, "num_filters_1": 24, "num_layers": 1, "optimizer": "Adam", "steps_to_train": 65, "weight_decay": 0.12664407768349378}, {"model_based_pick": false}]
[[1, 0, 6], {"batch_size": 64, "kernel_size_1": 7, "lr": 0.00840956786440588, "num_filters_1": 33, "num_layers": 1, "optimizer": "Adam", "steps_to_train": 10, "weight_decay": 0.13818547885959798}, {"model_based_pick": false}]
[[1, 0, 7], {"batch_size": 64, "kernel_size_1": 3, "lr": 0.0017523206235809967, "num_filters_1": 16, "num_layers": 3, "optimizer": "SGD", "steps_to_train": 45, "weight_decay": 0.1701750635039224, "kernel_size_2": 5, "kernel_size_3": 7, "num_filters_2": 22, "num_filters_3": 17}, {"model_based_pick": false}]
[[1, 0, 8], {"batch_size": 32, "kernel_size_1": 7, "lr": 0.005614280549391685, "num_filters_1": 44, "num_layers": 2, "optimizer": "Adam", "steps_to_train": 26, "weight_decay": 0.10329511211041377, "kernel_size_2": 5, "num_filters_2": 34}, {"model_based_pick": false}]
[[2, 0, 0], {"batch_size": 16, "kernel_size_1": 7, "lr": 0.07149033576084719, "num_filters_1": 98, "num_layers": 4, "optimizer": "SGD", "steps_to_train": 67, "weight_decay": 0.05672975854741957, "kernel_size_2": 3, "kernel_size_3": 3, "kernel_size_4": 7, "num_filters_2": 126, "num_filters_3": 77, "num_filters_4": 24}, {"model_based_pick": false}]
[[2, 0, 1], {"batch_size": 64, "kernel_size_1": 7, "lr": 0.018532644127432777, "num_filters_1": 30, "num_layers": 2, "optimizer": "Adam", "steps_to_train": 90, "weight_decay": 0.020650000158119495, "kernel_size_2": 5, "num_filters_2": 22}, {"model_based_pick": false}]
[[2, 0, 2], {"batch_size": 64, "kernel_size_1": 5, "lr": 0.002171929989288234, "num_filters_1": 17, "num_layers": 2, "optimizer": "Adam", "steps_to_train": 99, "weight_decay": 0.11231742341426457, "kernel_size_2": 5, "num_filters_2": 105}, {"model_based_pick": false}]
[[2, 0, 3], {"batch_size": 64, "kernel_size_1": 5, "lr": 0.023226774491594302, "num_filters_1": 27, "num_layers": 4, "optimizer": "SGD", "steps_to_train": 74, "weight_decay": 0.1784937697402036, "kernel_size_2": 3, "kernel_size_3": 5, "kernel_size_4": 7, "num_filters_2": 48, "num_filters_3": 34, "num_filters_4": 22}, {"model_based_pick": false}]
[[2, 0, 4], {"batch_size": 64, "kernel_size_1": 3, "lr": 0.0314115017560747, "num_filters_1": 29, "num_layers": 2, "optimizer": "SGD", "steps_to_train": 29, "weight_decay": 0.1054473645488371, "kernel_size_2": 7, "num_filters_2": 32}, {"model_based_pick": false}]
[[2, 0, 5], {"batch_size": 128, "kernel_size_1": 7, "lr": 0.002900784577426342, "num_filters_1": 39, "num_layers": 5, "optimizer": "SGD", "steps_to_train": 85, "weight_decay": 0.1179678659682594, "kernel_size_2": 3, "kernel_size_3": 3, "kernel_size_4": 5, "kernel_size_5": 5, "num_filters_2": 36, "num_filters_3": 20, "num_filters_4": 34, "num_filters_5": 19}, {"model_based_pick": false}]
[[3, 0, 0], {"batch_size": 16, "kernel_size_1": 5, "lr": 0.0012363333702699313, "num_filters_1": 47, "num_layers": 5, "optimizer": "SGD", "steps_to_train": 47, "weight_decay": 0.01853354496905626, "kernel_size_2": 3, "kernel_size_3": 3, "kernel_size_4": 5, "kernel_size_5": 3, "num_filters_2": 61, "num_filters_3": 61, "num_filters_4": 21, "num_filters_5": 21}, {"model_based_pick": false}]
[[3, 0, 1], {"batch_size": 32, "kernel_size_1": 7, "lr": 0.005104488522690003, "num_filters_1": 49, "num_layers": 2, "optimizer": "Adam", "steps_to_train": 34, "weight_decay": 0.11768648602592037, "kernel_size_2": 3, "num_filters_2": 24}, {"model_based_pick": false}]
[[3, 0, 2], {"batch_size": 32, "kernel_size_1": 7, "lr": 0.008724909798600883, "num_filters_1": 70, "num_layers": 4, "optimizer": "SGD", "steps_to_train": 41, "weight_decay": 0.08563258042341484, "kernel_size_2": 3, "kernel_size_3": 7, "kernel_size_4": 7, "num_filters_2": 39, "num_filters_3": 32, "num_filters_4": 26}, {"model_based_pick": false}]
[[3, 0, 3], {"batch_size": 16, "kernel_size_1": 3, "lr": 0.00175584561206751, "num_filters_1": 51, "num_layers": 1, "optimizer": "Adam", "steps_to_train": 92, "weight_decay": 0.027398200840728498}, {"model_based_pick": false}]
[[4, 0, 0], {"batch_size": 32, "kernel_size_1": 7, "lr": 0.007192656304196142, "num_filters_1": 20, "num_layers": 5, "optimizer": "SGD", "steps_to_train": 42, "weight_decay": 0.18906471861155014, "kernel_size_2": 5, "kernel_size_3": 7, "kernel_size_4": 3, "kernel_size_5": 5, "num_filters_2": 20, "num_filters_3": 18, "num_filters_4": 64, "num_filters_5": 19}, {"model_based_pick": false}]
[[4, 0, 1], {"batch_size": 32, "kernel_size_1": 3, "lr": 0.0011260679797578054, "num_filters_1": 30, "num_layers": 3, "optimizer": "Adam", "steps_to_train": 64, "weight_decay": 0.19693168170240732, "kernel_size_2": 7, "kernel_size_3": 5, "num_filters_2": 107, "num_filters_3": 66}, {"model_based_pick": false}]
[[4, 0, 2], {"batch_size": 16, "kernel_size_1": 7, "lr": 0.01730780209950449, "num_filters_1": 16, "num_layers": 2, "optimizer": "SGD", "steps_to_train": 93, "weight_decay": 0.040055697582989706, "kernel_size_2": 3, "num_filters_2": 69}, {"model_based_pick": false}]
[[4, 0, 3], {"batch_size": 128, "kernel_size_1": 3, "lr": 0.008156105389257668, "num_filters_1": 17, "num_layers": 5, "optimizer": "Adam", "steps_to_train": 35, "weight_decay": 0.07590063459008405, "kernel_size_2": 5, "kernel_size_3": 3, "kernel_size_4": 3, "kernel_size_5": 5, "num_filters_2": 16, "num_filters_3": 76, "num_filters_4": 22, "num_filters_5": 23}, {"model_based_pick": false}]
[[4, 0, 4], {"batch_size": 64, "kernel_size_1": 5, "lr": 0.016589632431904304, "num_filters_1": 24, "num_layers": 2, "optimizer": "Adam", "steps_to_train": 19, "weight_decay": 0.19636713181281934, "kernel_size_2": 7, "num_filters_2": 50}, {"model_based_pick": false}]
[[4, 0, 5], {"batch_size": 16, "kernel_size_1": 3, "lr": 0.03013195674945473, "num_filters_1": 63, "num_layers": 3, "optimizer": "SGD", "steps_to_train": 36, "weight_decay": 0.13791216682946442, "kernel_size_2": 7, "kernel_size_3": 5, "num_filters_2": 55, "num_filters_3": 88}, {"model_based_pick": false}]
[[4, 0, 6], {"batch_size": 64, "kernel_size_1": 5, "lr": 0.015265172825941451, "num_filters_1": 60, "num_layers": 1, "optimizer": "SGD", "steps_to_train": 10, "weight_decay": 0.10666171153906064}, {"model_based_pick": false}]
[[4, 0, 7], {"batch_size": 128, "kernel_size_1": 5, "lr": 0.0013342157985329662, "num_filters_1": 23, "num_layers": 4, "optimizer": "SGD", "steps_to_train": 91, "weight_decay": 0.059597486330360966, "kernel_size_2": 3, "kernel_size_3": 3, "kernel_size_4": 7, "num_filters_2": 93, "num_filters_3": 66, "num_filters_4": 91}, {"model_based_pick": false}]
[[4, 0, 8], {"batch_size": 32, "kernel_size_1": 7, "lr": 0.0036555897360090535, "num_filters_1": 121, "num_layers": 3, "optimizer": "Adam", "steps_to_train": 34, "weight_decay": 0.02656874055076459, "kernel_size_2": 7, "kernel_size_3": 5, "num_filters_2": 81, "num_filters_3": 36}, {"model_based_pick": false}]
[[4, 0, 9], {"batch_size": 64, "kernel_size_1": 3, "lr": 0.07150716884462235, "num_filters_1": 92, "num_layers": 5, "optimizer": "Adam", "steps_to_train": 97, "weight_decay": 0.04348660296509796, "kernel_size_2": 5, "kernel_size_3": 3, "kernel_size_4": 3, "kernel_size_5": 7, "num_filters_2": 27, "num_filters_3": 69, "num_filters_4": 42, "num_filters_5": 19}, {"model_based_pick": false}]
[[4, 0, 10], {"batch_size": 128, "kernel_size_1": 7, "lr": 0.0010648315794555005, "num_filters_1": 21, "num_layers": 1, "optimizer": "SGD", "steps_to_train": 65, "weight_decay": 0.07223064170691267}, {"model_based_pick": true}]
[[4, 0, 11], {"batch_size": 128, "kernel_size_1": 3, "lr": 0.012348897492018228, "num_filters_1": 40, "num_layers": 3, "optimizer": "SGD", "steps_to_train": 69, "weight_decay": 0.011410755051337935, "kernel_size_2": 7, "kernel_size_3": 5, "num_filters_2": 123, "num_filters_3": 57}, {"model_based_pick": false}]
[[4, 0, 12], {"batch_size": 16, "kernel_size_1": 5, "lr": 0.09028931095315061, "num_filters_1": 23, "num_layers": 1, "optimizer": "SGD", "steps_to_train": 69, "weight_decay": 0.18632261180347423}, {"model_based_pick": true}]
[[4, 0, 13], {"batch_size": 16, "kernel_size_1": 5, "lr": 0.05446428227569642, "num_filters_1": 33, "num_layers": 4, "optimizer": "SGD", "steps_to_train": 21, "weight_decay": 0.023006708676612763, "kernel_size_2": 3, "kernel_size_3": 7, "kernel_size_4": 3, "num_filters_2": 27, "num_filters_3": 112, "num_filters_4": 41}, {"model_based_pick": true}]
[[4, 0, 14], {"batch_size": 128, "kernel_size_1": 5, "lr": 0.022049801730139006, "num_filters_1": 79, "num_layers": 2, "optimizer": "SGD", "steps_to_train": 16, "weight_decay": 0.1549802541700692, "kernel_size_2": 7, "num_filters_2": 76}, {"model_based_pick": true}]
[[4, 0, 15], {"batch_size": 32, "kernel_size_1": 7, "lr": 0.001021750986738185, "num_filters_1": 23, "num_layers": 2, "optimizer": "SGD", "steps_to_train": 87, "weight_decay": 0.04090585563889075, "kernel_size_2": 3, "num_filters_2": 41}, {"model_based_pick": true}]
[[4, 0, 16], {"batch_size": 64, "kernel_size_1": 7, "lr": 0.027701210118223674, "num_filters_1": 103, "num_layers": 4, "optimizer": "SGD", "steps_to_train": 31, "weight_decay": 0.10751843631592393, "kernel_size_2": 3, "kernel_size_3": 5, "kernel_size_4": 3, "num_filters_2": 45, "num_filters_3": 126, "num_filters_4": 79}, {"model_based_pick": true}]
[[4, 0, 17], {"batch_size": 64, "kernel_size_1": 7, "lr": 0.005622085488695955, "num_filters_1": 111, "num_layers": 4, "optimizer": "SGD", "steps_to_train": 38, "weight_decay": 0.12032979299110845, "kernel_size_2": 7, "kernel_size_3": 7, "kernel_size_4": 3, "num_filters_2": 18, "num_filters_3": 16, "num_filters_4": 42}, {"model_based_pick": true}]
[[4, 0, 18], {"batch_size": 128, "kernel_size_1": 7, "lr": 0.002314379684184439, "num_filters_1": 28, "num_layers": 2, "optimizer": "SGD", "steps_to_train": 88, "weight_decay": 0.052419922436711605, "kernel_size_2": 5, "num_filters_2": 37}, {"model_based_pick": true}]
[[4, 0, 19], {"batch_size": 128, "kernel_size_1": 7, "lr": 0.0015182668744534882, "num_filters_1": 30, "num_layers": 2, "optimizer": "SGD", "steps_to_train": 63, "weight_decay": 0.08893933612523051, "kernel_size_2": 5, "num_filters_2": 55}, {"model_based_pick": false}]
[[4, 0, 20], {"batch_size": 128, "kernel_size_1": 3, "lr": 0.0017852967679260485, "num_filters_1": 21, "num_layers": 2, "optimizer": "Adam", "steps_to_train": 46, "weight_decay": 0.0972349610583077, "kernel_size_2": 7, "num_filters_2": 35}, {"model_based_pick": false}]
[[4, 0, 21], {"batch_size": 16, "kernel_size_1": 5, "lr": 0.013889804882443665, "num_filters_1": 51, "num_layers": 3, "optimizer": "Adam", "steps_to_train": 38, "weight_decay": 0.01602019805508198, "kernel_size_2": 5, "kernel_size_3": 7, "num_filters_2": 67, "num_filters_3": 20}, {"model_based_pick": false}]
[[4, 0, 22], {"batch_size": 64, "kernel_size_1": 3, "lr": 0.010923173113799816, "num_filters_1": 89, "num_layers": 1, "optimizer": "Adam", "steps_to_train": 100, "weight_decay": 0.011789671106613542}, {"model_based_pick": false}]
[[4, 0, 23], {"batch_size": 16, "kernel_size_1": 7, "lr": 0.015537303414282309, "num_filters_1": 36, "num_layers": 2, "optimizer": "SGD", "steps_to_train": 24, "weight_decay": 0.07135290065649663, "kernel_size_2": 3, "num_filters_2": 18}, {"model_based_pick": false}]
[[4, 0, 24], {"batch_size": 64, "kernel_size_1": 3, "lr": 0.03798767152452291, "num_filters_1": 24, "num_layers": 5, "optimizer": "SGD", "steps_to_train": 90, "weight_decay": 0.11585481073208052, "kernel_size_2": 5, "kernel_size_3": 3, "kernel_size_4": 7, "kernel_size_5": 5, "num_filters_2": 64, "num_filters_3": 22, "num_filters_4": 36, "num_filters_5": 19}, {"model_based_pick": true}]
[[4, 0, 25], {"batch_size": 64, "kernel_size_1": 3, "lr": 0.0015661113606992595, "num_filters_1": 101, "num_layers": 2, "optimizer": "SGD", "steps_to_train": 30, "weight_decay": 0.04663961914725411, "kernel_size_2": 7, "num_filters_2": 22}, {"model_based_pick": false}]
[[4, 0, 26], {"batch_size": 64, "kernel_size_1": 7, "lr": 0.0025456255272496052, "num_filters_1": 21, "num_layers": 2, "optimizer": "SGD", "steps_to_train": 15, "weight_decay": 0.07286766249387397, "kernel_size_2": 5, "num_filters_2": 69}, {"model_based_pick": true}]
[[5, 0, 0], {"batch_size": 128, "kernel_size_1": 3, "lr": 0.0016610086119991441, "num_filters_1": 103, "num_layers": 5, "optimizer": "Adam", "steps_to_train": 76, "weight_decay": 0.03350590634266199, "kernel_size_2": 7, "kernel_size_3": 7, "kernel_size_4": 7, "kernel_size_5": 7, "num_filters_2": 23, "num_filters_3": 35, "num_filters_4": 87, "num_filters_5": 115}, {"model_based_pick": false}]
[[5, 0, 1], {"batch_size": 64, "kernel_size_1": 5, "lr": 0.002052732017736559, "num_filters_1": 18, "num_layers": 2, "optimizer": "Adam", "steps_to_train": 55, "weight_decay": 0.07346528436593405, "kernel_size_2": 7, "num_filters_2": 38}, {"model_based_pick": true}]
[[5, 0, 2], {"batch_size": 128, "kernel_size_1": 3, "lr": 0.0013395240112611608, "num_filters_1": 74, "num_layers": 4, "optimizer": "SGD", "steps_to_train": 72, "weight_decay": 0.015929825201362078, "kernel_size_2": 3, "kernel_size_3": 5, "kernel_size_4": 3, "num_filters_2": 32, "num_filters_3": 104, "num_filters_4": 75}, {"model_based_pick": true}]
[[5, 0, 3], {"batch_size": 32, "kernel_size_1": 5, "lr": 0.0037927467683851494, "num_filters_1": 128, "num_layers": 2, "optimizer": "SGD", "steps_to_train": 29, "weight_decay": 0.07147476449348472, "kernel_size_2": 3, "num_filters_2": 82}, {"model_based_pick": true}]
[[5, 0, 4], {"batch_size": 16, "kernel_size_1": 7, "lr": 0.005007580997267822, "num_filters_1": 122, "num_layers": 5, "optimizer": "SGD", "steps_to_train": 35, "weight_decay": 0.19546190432453708, "kernel_size_2": 3, "kernel_size_3": 5, "kernel_size_4": 3, "kernel_size_5": 7, "num_filters_2": 26, "num_filters_3": 47, "num_filters_4": 89, "num_filters_5": 16}, {"model_based_pick": false}]
[[5, 0, 5], {"batch_size": 32, "kernel_size_1": 5, "lr": 0.0192638294753484, "num_filters_1": 16, "num_layers": 3, "optimizer": "SGD", "steps_to_train": 66, "weight_decay": 0.09773830579537682, "kernel_size_2": 3, "kernel_size_3": 5, "num_filters_2": 51, "num_filters_3": 69}, {"model_based_pick": true}]
[[5, 0, 6], {"batch_size": 128, "kernel_size_1": 5, "lr": 0.014437380074937004, "num_filters_1": 103, "num_layers": 1, "optimizer": "Adam", "steps_to_train": 25, "weight_decay": 0.08977164150786372}, {"model_based_pick": true}]
[[5, 0, 7], {"batch_size": 128, "kernel_size_1": 3, "lr": 0.004704065089192004, "num_filters_1": 24, "num_layers": 4, "optimizer": "Adam", "steps_to_train": 93, "weight_decay": 0.03313697450545084, "kernel_size_2": 5, "kernel_size_3": 5, "kernel_size_4": 3, "num_filters_2": 22, "num_filters_3": 67, "num_filters_4": 78}, {"model_based_pick": false}]
[[5, 0, 8], {"batch_size": 128, "kernel_size_1": 3, "lr": 0.019747613735300568, "num_filters_1": 111, "num_layers": 2, "optimizer": "SGD", "steps_to_train": 55, "weight_decay": 0.04230843007417595, "kernel_size_2": 7, "num_filters_2": 99}, {"model_based_pick": true}]
[[6, 0, 0], {"batch_size": 16, "kernel_size_1": 5, "lr": 0.0010934348089019488, "num_filters_1": 94, "num_layers": 1, "optimizer": "Adam", "steps_to_train": 11, "weight_decay": 0.05643731487286155}, {"model_based_pick": true}]
[[6, 0, 1], {"batch_size": 128, "kernel_size_1": 3, "lr": 0.04099156443839571, "num_filters_1": 77, "num_layers": 3, "optimizer": "SGD", "steps_to_train": 63, "weight_decay": 0.01083280690518948, "kernel_size_2": 7, "kernel_size_3": 3, "num_filters_2": 52, "num_filters_3": 59}, {"model_based_pick": true}]
[[6, 0, 2], {"batch_size": 128, "kernel_size_1": 3, "lr": 0.0018897611708380755, "num_filters_1": 123, "num_layers": 1, "optimizer": "SGD", "steps_to_train": 66, "weight_decay": 0.01583591665773248}, {"model_based_pick": true}]
[[6, 0, 3], {"batch_size": 32, "kernel_size_1": 5, "lr": 0.07659671364121412, "num_filters_1": 27, "num_layers": 4, "optimizer": "SGD", "steps_to_train": 19, "weight_decay": 0.07535944286232224, "kernel_size_2": 7, "kernel_size_3": 5, "kernel_size_4": 5, "num_filters_2": 20, "num_filters_3": 42, "num_filters_4": 34}, {"model_based_pick": true}]
[[6, 0, 4], {"batch_size": 128, "kernel_size_1": 3, "lr": 0.00552718783895901, "num_filters_1": 96, "num_layers": 1, "optimizer": "SGD", "steps_to_train": 62, "weight_decay": 0.022841151109546345}, {"model_based_pick": true}]
[[6, 0, 5], {"batch_size": 128, "kernel_size_1": 5, "lr": 0.00438904377243131, "num_filters_1": 30, "num_layers": 3, "optimizer": "SGD", "steps_to_train": 60, "weight_decay": 0.057226397962396765, "kernel_size_2": 5, "kernel_size_3": 7, "num_filters_2": 62, "num_filters_3": 50}, {"model_based_pick": true}]
[[7, 0, 0], {"batch_size": 128, "kernel_size_1": 5, "lr": 0.049850471461866976, "num_filters_1": 65, "num_layers": 1, "optimizer": "Adam", "steps_to_train": 24, "weight_decay": 0.04586231304113253}, {"model_based_pick": false}]
[[7, 0, 1], {"batch_size": 128, "kernel_size_1": 3, "lr": 0.0022347647448711103, "num_filters_1": 93, "num_layers": 2, "optimizer": "Adam", "steps_to_train": 40, "weight_decay": 0.011778119284672746, "kernel_size_2": 5, "num_filters_2": 21}, {"model_based_pick": true}]
[[7, 0, 2], {"batch_size": 16, "kernel_size_1": 7, "lr": 0.002194015925861027, "num_filters_1": 93, "num_layers": 3, "optimizer": "Adam", "steps_to_train": 41, "weight_decay": 0.115964154050317, "kernel_size_2": 7, "kernel_size_3": 5, "num_filters_2": 83, "num_filters_3": 47}, {"model_based_pick": false}]
[[7, 0, 3], {"batch_size": 128, "kernel_size_1": 3, "lr": 0.006262820361141908, "num_filters_1": 17, "num_layers": 4, "optimizer": "SGD", "steps_to_train": 43, "weight_decay": 0.03105060349311125, "kernel_size_2": 3, "kernel_size_3": 5, "kernel_size_4": 5, "num_filters_2": 23, "num_filters_3": 35, "num_filters_4": 115}, {"model_based_pick": true}]
[[8, 0, 0], {"batch_size": 128, "kernel_size_1": 7, "lr": 0.008882654491251684, "num_filters_1": 78, "num_layers": 3, "optimizer": "Adam", "steps_to_train": 53, "weight_decay": 0.024157997472262896, "kernel_size_2": 3, "kernel_size_3": 3, "num_filters_2": 60, "num_filters_3": 16}, {"model_based_pick": false}]
[[8, 0, 1], {"batch_size": 64, "kernel_size_1": 7, "lr": 0.011263945812509751, "num_filters_1": 30, "num_layers": 3, "optimizer": "SGD", "steps_to_train": 17, "weight_decay": 0.11206981117180015, "kernel_size_2": 7, "kernel_size_3": 3, "num_filters_2": 18, "num_filters_3": 28}, {"model_based_pick": false}]
[[8, 0, 2], {"batch_size": 128, "kernel_size_1": 5, "lr": 0.084126609489751, "num_filters_1": 65, "num_layers": 1, "optimizer": "Adam", "steps_to_train": 64, "weight_decay": 0.09636310650788256}, {"model_based_pick": true}]
[[8, 0, 3], {"batch_size": 128, "kernel_size_1": 5, "lr": 0.0035934002850068892, "num_filters_1": 18, "num_layers": 3, "optimizer": "SGD", "steps_to_train": 86, "weight_decay": 0.07892365823797745, "kernel_size_2": 7, "kernel_size_3": 7, "num_filters_2": 78, "num_filters_3": 57}, {"model_based_pick": true}]
[[8, 0, 4], {"batch_size": 128, "kernel_size_1": 5, "lr": 0.0019834669400632574, "num_filters_1": 57, "num_layers": 1, "optimizer": "SGD", "steps_to_train": 50, "weight_decay": 0.026809842649716004}, {"model_based_pick": true}]
[[8, 0, 5], {"batch_size": 16, "kernel_size_1": 7, "lr": 0.00431073851022361, "num_filters_1": 43, "num_layers": 1, "optimizer": "SGD", "steps_to_train": 15, "weight_decay": 0.04385693756219116}, {"model_based_pick": false}]
[[8, 0, 6], {"batch_size": 128, "kernel_size_1": 5, "lr": 0.011742744633905162, "num_filters_1": 40, "num_layers": 1, "optimizer": "SGD", "steps_to_train": 100, "weight_decay": 0.04533808430723868}, {"model_based_pick": false}]
[[8, 0, 7], {"batch_size": 128, "kernel_size_1": 3, "lr": 0.04624349328365757, "num_filters_1": 52, "num_layers": 3, "optimizer": "Adam", "steps_to_train": 75, "weight_decay": 0.040123642956024524, "kernel_size_2": 7, "kernel_size_3": 7, "num_filters_2": 35, "num_filters_3": 52}, {"model_based_pick": true}]
[[8, 0, 8], {"batch_size": 32, "kernel_size_1": 5, "lr": 0.001343892077049151, "num_filters_1": 74, "num_layers": 1, "optimizer": "SGD", "steps_to_train": 25, "weight_decay": 0.1159842433535904}, {"model_based_pick": true}]
[[8, 0, 9], {"batch_size": 128, "kernel_size_1": 7, "lr": 0.036923452848424215, "num_filters_1": 59, "num_layers": 3, "optimizer": "SGD", "steps_to_train": 36, "weight_decay": 0.026780042876544216, "kernel_size_2": 3, "kernel_size_3": 5, "num_filters_2": 40, "num_filters_3": 81}, {"model_based_pick": true}]
[[8, 0, 10], {"batch_size": 128, "kernel_size_1": 5, "lr": 0.006588473724102132, "num_filters_1": 106, "num_layers": 3, "optimizer": "SGD", "steps_to_train": 37, "weight_decay": 0.01064384022884375, "kernel_size_2": 7, "kernel_size_3": 7, "num_filters_2": 121, "num_filters_3": 110}, {"model_based_pick": true}]
[[8, 0, 11], {"batch_size": 32, "kernel_size_1": 5, "lr": 0.001134449010822172, "num_filters_1": 83, "num_layers": 3, "optimizer": "Adam", "steps_to_train": 31, "weight_decay": 0.159674012383078, "kernel_size_2": 3, "kernel_size_3": 3, "num_filters_2": 93, "num_filters_3": 106}, {"model_based_pick": false}]
[[8, 0, 12], {"batch_size": 16, "kernel_size_1": 5, "lr": 0.03167366042107443, "num_filters_1": 20, "num_layers": 5, "optimizer": "SGD", "steps_to_train": 55, "weight_decay": 0.011564042938884769, "kernel_size_2": 5, "kernel_size_3": 3, "kernel_size_4": 5, "kernel_size_5": 7, "num_filters_2": 24, "num_filters_3": 93, "num_filters_4": 29, "num_filters_5": 42}, {"model_based_pick": true}]
[[8, 0, 13], {"batch_size": 128, "kernel_size_1": 7, "lr": 0.0013342982287576476, "num_filters_1": 108, "num_layers": 2, "optimizer": "SGD", "steps_to_train": 42, "weight_decay": 0.040007764472362074, "kernel_size_2": 5, "num_filters_2": 61}, {"model_based_pick": true}]
[[8, 0, 14], {"batch_size": 128, "kernel_size_1": 7, "lr": 0.0021997262645747514, "num_filters_1": 31, "num_layers": 1, "optimizer": "SGD", "steps_to_train": 78, "weight_decay": 0.01568786901024944}, {"model_based_pick": true}]
[[8, 0, 15], {"batch_size": 128, "kernel_size_1": 3, "lr": 0.0013919509923957906, "num_filters_1": 28, "num_layers": 4, "optimizer": "Adam", "steps_to_train": 43, "weight_decay": 0.09354884301834986, "kernel_size_2": 5, "kernel_size_3": 5, "kernel_size_4": 7, "num_filters_2": 40, "num_filters_3": 61, "num_filters_4": 64}, {"model_based_pick": true}]
[[8, 0, 16], {"batch_size": 32, "kernel_size_1": 3, "lr": 0.0010381613260989897, "num_filters_1": 21, "num_layers": 4, "optimizer": "SGD", "steps_to_train": 12, "weight_decay": 0.17231573043158288, "kernel_size_2": 5, "kernel_size_3": 3, "kernel_size_4": 7, "num_filters_2": 21, "num_filters_3": 16, "num_filters_4": 31}, {"model_based_pick": true}]
[[8, 0, 17], {"batch_size": 64, "kernel_size_1": 7, "lr": 0.021950217973278726, "num_filters_1": 114, "num_layers": 5, "optimizer": "SGD", "steps_to_train": 48, "weight_decay": 0.01339136187828911, "kernel_size_2": 5, "kernel_size_3": 7, "kernel_size_4": 3, "kernel_size_5": 5, "num_filters_2": 51, "num_filters_3": 117, "num_filters_4": 81, "num_filters_5": 41}, {"model_based_pick": false}]
[[8, 0, 18], {"batch_size": 128, "kernel_size_1": 3, "lr": 0.001910919509196054, "num_filters_1": 98, "num_layers": 2, "optimizer": "SGD", "steps_to_train": 100, "weight_decay": 0.032123518363210396, "kernel_size_2": 3, "num_filters_2": 47}, {"model_based_pick": true}]
[[8, 0, 19], {"batch_size": 32, "kernel_size_1": 3, "lr": 0.014496777912752409, "num_filters_1": 17, "num_layers": 1, "optimizer": "SGD", "steps_to_train": 95, "weight_decay": 0.05721036957144495}, {"model_based_pick": true}]
[[8, 0, 20], {"batch_size": 128, "kernel_size_1": 7, "lr": 0.006445088223152506, "num_filters_1": 18, "num_layers": 4, "optimizer": "SGD", "steps_to_train": 75, "weight_decay": 0.11456434019815624, "kernel_size_2": 7, "kernel_size_3": 5, "kernel_size_4": 5, "num_filters_2": 19, "num_filters_3": 62, "num_filters_4": 63}, {"model_based_pick": true}]
[[8, 0, 21], {"batch_size": 128, "kernel_size_1": 3, "lr": 0.004386085438391888, "num_filters_1": 46, "num_layers": 4, "optimizer": "SGD", "steps_to_train": 66, "weight_decay": 0.02048148415798362, "kernel_size_2": 7, "kernel_size_3": 3, "kernel_size_4": 3, "num_filters_2": 28, "num_filters_3": 25, "num_filters_4": 114}, {"model_based_pick": true}]
[[8, 0, 22], {"batch_size": 128, "kernel_size_1": 5, "lr": 0.05425608447009259, "num_filters_1": 30, "num_layers": 1, "optimizer": "SGD", "steps_to_train": 16, "weight_decay": 0.043997034288169576}, {"model_based_pick": true}]
[[8, 0, 23], {"batch_size": 128, "kernel_size_1": 3, "lr": 0.017236424044403596, "num_filters_1": 38, "num_layers": 4, "optimizer": "Adam", "steps_to_train": 57, "weight_decay": 0.01941281489849239, "kernel_size_2": 7, "kernel_size_3": 3, "kernel_size_4": 3, "num_filters_2": 41, "num_filters_3": 24, "num_filters_4": 113}, {"model_based_pick": true}]
[[8, 0, 24], {"batch_size": 64, "kernel_size_1": 3, "lr": 0.024422942299863155, "num_filters_1": 40, "num_layers": 1, "optimizer": "SGD", "steps_to_train": 91, "weight_decay": 0.10423979521255922}, {"model_based_pick": false}]
[[8, 0, 25], {"batch_size": 64, "kernel_size_1": 5, "lr": 0.021669030038248382, "num_filters_1": 16, "num_layers": 3, "optimizer": "SGD", "steps_to_train": 62, "weight_decay": 0.04290316413098935, "kernel_size_2": 7, "kernel_size_3": 7, "num_filters_2": 82, "num_filters_3": 103}, {"model_based_pick": false}]
[[8, 0, 26], {"batch_size": 128, "kernel_size_1": 3, "lr": 0.026085255387411157, "num_filters_1": 51, "num_layers": 5, "optimizer": "SGD", "steps_to_train": 22, "weight_decay": 0.016158456596486768, "kernel_size_2": 3, "kernel_size_3": 7, "kernel_size_4": 5, "kernel_size_5": 7, "num_filters_2": 56, "num_filters_3": 48, "num_filters_4": 25, "num_filters_5": 42}, {"model_based_pick": true}]
[[9, 0, 0], {"batch_size": 128, "kernel_size_1": 5, "lr": 0.03177242672703801, "num_filters_1": 59, "num_layers": 2, "optimizer": "SGD", "steps_to_train": 77, "weight_decay": 0.14132120300255616, "kernel_size_2": 3, "num_filters_2": 51}, {"model_based_pick": true}]
[[9, 0, 1], {"batch_size": 128, "kernel_size_1": 3, "lr": 0.0019438941812683882, "num_filters_1": 113, "num_layers": 2, "optimizer": "Adam", "steps_to_train": 18, "weight_decay": 0.02133111640169232, "kernel_size_2": 5, "num_filters_2": 22}, {"model_based_pick": true}]
[[9, 0, 2], {"batch_size": 128, "kernel_size_1": 7, "lr": 0.008800704450608605, "num_filters_1": 20, "num_layers": 4, "optimizer": "SGD", "steps_to_train": 47, "weight_decay": 0.1363074539710253, "kernel_size_2": 3, "kernel_size_3": 7, "kernel_size_4": 7, "num_filters_2": 28, "num_filters_3": 104, "num_filters_4": 52}, {"model_based_pick": true}]
[[9, 0, 3], {"batch_size": 128, "kernel_size_1": 7, "lr": 0.014176222483837672, "num_filters_1": 47, "num_layers": 1, "optimizer": "SGD", "steps_to_train": 40, "weight_decay": 0.020501214493904907}, {"model_based_pick": true}]
[[9, 0, 4], {"batch_size": 16, "kernel_size_1": 5, "lr": 0.07792114055000547, "num_filters_1": 48, "num_layers": 2, "optimizer": "SGD", "steps_to_train": 46, "weight_decay": 0.023909838879083097, "kernel_size_2": 7, "num_filters_2": 17}, {"model_based_pick": false}]
[[9, 0, 5], {"batch_size": 64, "kernel_size_1": 5, "lr": 0.012961395241726395, "num_filters_1": 47, "num_layers": 4, "optimizer": "Adam", "steps_to_train": 46, "weight_decay": 0.012819937537144879, "kernel_size_2": 5, "kernel_size_3": 3, "kernel_size_4": 5, "num_filters_2": 57, "num_filters_3": 36, "num_filters_4": 25}, {"model_based_pick": false}]
[[9, 0, 6], {"batch_size": 128, "kernel_size_1": 5, "lr": 0.023667727439693073, "num_filters_1": 60, "num_layers": 2, "optimizer": "Adam", "steps_to_train": 24, "weight_decay": 0.02607482936429502, "kernel_size_2": 5, "num_filters_2": 56}, {"model_based_pick": true}]
[[9, 0, 7], {"batch_size": 128, "kernel_size_1": 7, "lr": 0.004964236517245561, "num_filters_1": 96, "num_layers": 3, "optimizer": "SGD", "steps_to_train": 82, "weight_decay": 0.019483965081934417, "kernel_size_2": 3, "kernel_size_3": 3, "num_filters_2": 54, "num_filters_3": 66}, {"model_based_pick": true}]
[[9, 0, 8], {"batch_size": 128, "kernel_size_1": 5, "lr": 0.005228853196440936, "num_filters_1": 45, "num_layers": 4, "optimizer": "Adam", "steps_to_train": 41, "weight_decay": 0.012064202955980102, "kernel_size_2": 3, "kernel_size_3": 5, "kernel_size_4": 7, "num_filters_2": 58, "num_filters_3": 106, "num_filters_4": 36}, {"model_based_pick": false}]
